alteryse/__init__.py
alteryse/text_generation.py
alteryse/types.py
alteryse_py-0.1.0.dist-info/METADATA
alteryse_py-0.1.0.dist-info/WHEEL
alteryse_py-0.1.0.dist-info/top_level.txt
alteryse_py-0.1.0.dist-info/RECORD
