Metadata-Version: 2.1
Name: alteryse-py
Version: 0.1.0
Summary: A Python library for interacting with Alteryse Instances.
Home-page: https://github.com/alteryse/alteryse-py
Author: Alteryse
Author-email: hello@alteryse.cloud
Classifier: Programming Language :: Python :: 3
Classifier: License :: OSI Approved :: MIT License
Classifier: Operating System :: OS Independent
Requires-Python: >=3.6
